{
    "title": "Kubernetes Pipelines",
    "icon": "fa-kubernetes",
    "description": "Откройте для себя различные инструменты и техники для непрерывной доставки в Kubernetes.",
    "courses": [
      {
        "course_id": "registries",
        "title": "Container Registry",
        "description": "Изучите, как настроить и взаимодействовать с реестром private container registry в Kubernetes."
      },
      {
        "course_id": "harbor",
        "title": "Harbor Registry",
        "description": "Изучите, как реестр Harbor registry обеспечивает богатые возможности, наряду со сканированием Clair security scanning." 
      },
      {
        "course_id": "tekton",
        "title": "Tekton Pipelines",
        "description": "Билдинг и развертывание приложения Node.js с Tekton Pipeline."
      },
      {
        "course_id": "helm",
        "title": "Helm",
        "description": "Изучите, как использовать Helm, менеджер пакетов для Kubernetes."
      },
      {
        "course_id": "sonarqube",
        "title": "SonarQube",
        "description": "Анализ кода с помощью SonarQube в Kubernetes."
      }
    ]
  }
  